bookied_sync/__init__.py
bookied_sync/bettingmarket.py
bookied_sync/bettingmarketgroup.py
bookied_sync/bettingmarketgroupresolve.py
bookied_sync/comparators.py
bookied_sync/event.py
bookied_sync/eventgroup.py
bookied_sync/eventstatus.py
bookied_sync/exceptions.py
bookied_sync/lookup.py
bookied_sync/participant.py
bookied_sync/rule.py
bookied_sync/sport.py
bookied_sync/substitutions.py
bookied_sync/update.py
bookied_sync/utils.py
bos_sync-0.4.3.dist-info/LICENSE.txt
bos_sync-0.4.3.dist-info/METADATA
bos_sync-0.4.3.dist-info/WHEEL
bos_sync-0.4.3.dist-info/entry_points.txt
bos_sync-0.4.3.dist-info/top_level.txt
bos_sync-0.4.3.dist-info/RECORD
