Metadata-Version: 2.1
Name: bos-sync
Version: 0.4.3
Summary: Synchronized objects on the blockchain using proposals wherenecessary
Home-page: http://pbsa.info
Author: Peerplays Community
Maintainer: Peerplays Community
License: UNKNOWN
Download-URL: https://github.com/pbsa/bos-sync/tarball/0.4.3
Keywords: peerplays,bos
Platform: UNKNOWN
Classifier: License :: OSI Approved :: GNU General Public License v3 (GPLv3)
Classifier: Operating System :: OS Independent
Classifier: Programming Language :: Python :: 3
Classifier: Development Status :: 3 - Alpha
Classifier: Intended Audience :: Developers
Requires-Dist: peerplays (>=0.3.6)
Requires-Dist: bookiesports
Requires-Dist: pyyaml
Requires-Dist: colorlog
Requires-Dist: dateutils
